{
  "main": {
    "id": "3ac74ce95c880ec5",
    "type": "split",
    "children": [
      {
        "id": "d12a5476e571f6b7",
        "type": "tabs",
        "children": [
          {
            "id": "ab76de36e0c4c2c4",
            "type": "leaf",
            "state": {
              "type": "markdown",
              "state": {
                "file": "05 - Frameworks (CCM e CORBA)/CORBA.md",
                "mode": "source",
                "source": false
              },
              "icon": "lucide-file",
              "title": "CORBA"
            }
          }
        ]
      }
    ],
    "direction": "vertical"
  },
  "left": {
    "id": "f61d2e2436aa9bb1",
    "type": "split",
    "children": [
      {
        "id": "7a4b9eb646115feb",
        "type": "tabs",
        "children": [
          {
            "id": "0b8ba432abdf354d",
            "type": "leaf",
            "state": {
              "type": "file-explorer",
              "state": {
                "sortOrder": "alphabetical",
                "autoReveal": false
              },
              "icon": "lucide-folder-closed",
              "title": "Explorador de arquivos"
            }
          },
          {
            "id": "907f3f834fd2389c",
            "type": "leaf",
            "state": {
              "type": "search",
              "state": {
                "query": "",
                "matchingCase": false,
                "explainSearch": false,
                "collapseAll": false,
                "extraContext": false,
                "sortOrder": "alphabetical"
              },
              "icon": "lucide-search",
              "title": "Procurar"
            }
          },
          {
            "id": "7bd9520fb77bc94f",
            "type": "leaf",
            "state": {
              "type": "bookmarks",
              "state": {},
              "icon": "lucide-bookmark",
              "title": "Marcadores"
            }
          }
        ]
      }
    ],
    "direction": "horizontal",
    "width": 300
  },
  "right": {
    "id": "046b3a057c070010",
    "type": "split",
    "children": [
      {
        "id": "f923b1db4f4fc9ad",
        "type": "tabs",
        "children": [
          {
            "id": "bb4bf267f7c4199e",
            "type": "leaf",
            "state": {
              "type": "backlink",
              "state": {
                "file": "Garantia da Qualidade.md",
                "collapseAll": false,
                "extraContext": false,
                "sortOrder": "alphabetical",
                "showSearch": false,
                "searchQuery": "",
                "backlinkCollapsed": false,
                "unlinkedCollapsed": true
              },
              "icon": "links-coming-in",
              "title": "Links inversos para Garantia da Qualidade"
            }
          },
          {
            "id": "02dd894dd6363d27",
            "type": "leaf",
            "state": {
              "type": "outgoing-link",
              "state": {
                "file": "Garantia da Qualidade.md",
                "linksCollapsed": false,
                "unlinkedCollapsed": true
              },
              "icon": "links-going-out",
              "title": "Links de saída para Garantia da Qualidade"
            }
          },
          {
            "id": "b2fafcb133b64b30",
            "type": "leaf",
            "state": {
              "type": "tag",
              "state": {
                "sortOrder": "frequency",
                "useHierarchy": true,
                "showSearch": false,
                "searchQuery": ""
              },
              "icon": "lucide-tags",
              "title": "Etiquetas"
            }
          },
          {
            "id": "9e25bc387152c696",
            "type": "leaf",
            "state": {
              "type": "all-properties",
              "state": {
                "sortOrder": "frequency",
                "showSearch": false,
                "searchQuery": ""
              },
              "icon": "lucide-archive",
              "title": "Todas as propriedades"
            }
          },
          {
            "id": "95323911cd855e95",
            "type": "leaf",
            "state": {
              "type": "outline",
              "state": {
                "file": "Garantia da Qualidade.md",
                "followCursor": false,
                "showSearch": false,
                "searchQuery": ""
              },
              "icon": "lucide-list",
              "title": "Sumário de Garantia da Qualidade"
            }
          }
        ]
      }
    ],
    "direction": "horizontal",
    "width": 300,
    "collapsed": true
  },
  "left-ribbon": {
    "hiddenItems": {
      "switcher:Abrir a troca rápida": false,
      "graph:Abrir visualização em gráfico": false,
      "canvas:Criar novo canvas": false,
      "daily-notes:Abrir a nota de hoje": false,
      "templates:Inserir modelo": false,
      "command-palette:Abrir paleta de comandos": false,
      "bases:Criar nova base": false
    }
  },
  "active": "ab76de36e0c4c2c4",
  "lastOpenFiles": [
    "quiz/data/questoes.js.tmp.18116.a9de0a13990f",
    "07 - Simulados/Simulado 1 - Provisionamento e Componentes.md.tmp.18116.5f1a3a4d593e",
    "Bem-vindo.md.tmp.18116.d7cf3b12657a",
    "Bem-vindo.md.tmp.18116.40dcae87c78a",
    "Bem-vindo.md.tmp.18116.031e6c6f438f",
    "Bem-vindo.md.tmp.18116.0b13a9a2f40c",
    "Bem-vindo.md.tmp.18116.814b07f097ce",
    "08 - Processos e Gestão/Grupos de Processos de Projeto.md",
    "08 - Processos e Gestão/Grupos de Processos de Projeto.md.tmp.18116.5f8b123f6035",
    "08 - Processos e Gestão/Modelos de Desenvolvimento.md",
    "08 - Processos e Gestão/Modelos de Desenvolvimento.md.tmp.18116.a8773ce8d9e6",
    "06 - Referência/Arquitetura em Camadas.md",
    "06 - Referência/Arquitetura em Camadas.md.tmp.18116.02772bdb979f",
    "01 - Fundamentos/Casos de Uso - include x extend.md",
    "01 - Fundamentos/Casos de Uso - include x extend.md.tmp.18116.85e336c346d7",
    "01 - Fundamentos/Níveis de Modelo.md",
    "07 - Simulados/Simulado 1 - Provisionamento e Componentes.md",
    "01 - Fundamentos/Acoplamento e Coesão.md",
    "01 - Fundamentos/Abstração.md",
    "02 - Componentes/Componentes.md",
    "02 - Componentes/Empacotamento de Componentes.md",
    "02 - Componentes/Granularidade de Componentes.md",
    "02 - Componentes/Interação com Sistemas Existentes.md",
    "01 - Fundamentos/Princípio de Substituição de Liskov.md",
    "01 - Fundamentos/Interfaces e Contratos.md",
    "01 - Fundamentos/Múltiplas Interfaces.md",
    "Sem título 2.canvas",
    "Sem título.canvas",
    "Sem título 1.canvas",
    "03 - Implementação e Qualidade/Implementação de Componentes.md",
    "04 - Distribuição e Ambientes/Serviços de Infraestrutura.md",
    "04 - Distribuição e Ambientes/Programação Orientada a Aspectos.md",
    "04 - Distribuição e Ambientes/Programação Declarativa.md",
    "04 - Distribuição e Ambientes/Middleware.md",
    "04 - Distribuição e Ambientes/Ambiente de Componentes.md",
    "03 - Implementação e Qualidade/Especificação vs Construção de Componentes.md",
    "02 - Componentes/Padrão Factory.md",
    "03 - Implementação e Qualidade/Garantia da Qualidade.md",
    "06 - Referência/Clean Architecture.md"
  ]
}